httpie/__init__.py
httpie/__main__.py
httpie/adapters.py
httpie/client.py
httpie/compat.py
httpie/config.py
httpie/context.py
httpie/cookies.py
httpie/core.py
httpie/downloads.py
httpie/encoding.py
httpie/models.py
httpie/sessions.py
httpie/ssl_.py
httpie/status.py
httpie/uploads.py
httpie/utils.py
httpie/cli/__init__.py
httpie/cli/argparser.py
httpie/cli/argtypes.py
httpie/cli/constants.py
httpie/cli/definition.py
httpie/cli/dicts.py
httpie/cli/exceptions.py
httpie/cli/options.py
httpie/cli/requestitems.py
httpie/cli/utils.py
httpie/cli/nested_json/__init__.py
httpie/cli/nested_json/errors.py
httpie/cli/nested_json/interpret.py
httpie/cli/nested_json/parse.py
httpie/cli/nested_json/tokens.py
httpie/internal/__build_channel__.py
httpie/internal/__init__.py
httpie/internal/daemon_runner.py
httpie/internal/daemons.py
httpie/internal/update_warnings.py
httpie/legacy/__init__.py
httpie/legacy/v3_1_0_session_cookie_format.py
httpie/legacy/v3_2_0_session_header_format.py
httpie/manager/__init__.py
httpie/manager/__main__.py
httpie/manager/cli.py
httpie/manager/compat.py
httpie/manager/core.py
httpie/manager/tasks/__init__.py
httpie/manager/tasks/check_updates.py
httpie/manager/tasks/export_args.py
httpie/manager/tasks/plugins.py
httpie/manager/tasks/sessions.py
httpie/output/__init__.py
httpie/output/models.py
httpie/output/processing.py
httpie/output/streams.py
httpie/output/utils.py
httpie/output/writer.py
httpie/output/formatters/__init__.py
httpie/output/formatters/colors.py
httpie/output/formatters/headers.py
httpie/output/formatters/json.py
httpie/output/formatters/xml.py
httpie/output/lexers/__init__.py
httpie/output/lexers/common.py
httpie/output/lexers/http.py
httpie/output/lexers/json.py
httpie/output/lexers/metadata.py
httpie/output/ui/__init__.py
httpie/output/ui/man_pages.py
httpie/output/ui/palette.py
httpie/output/ui/rich_help.py
httpie/output/ui/rich_palette.py
httpie/output/ui/rich_progress.py
httpie/output/ui/rich_utils.py
httpie/plugins/__init__.py
httpie-3.2.4.dist-info/AUTHORS.md
httpie-3.2.4.dist-info/LICENSE
httpie-3.2.4.dist-info/METADATA
httpie-3.2.4.dist-info/WHEEL
httpie-3.2.4.dist-info/entry_points.txt
httpie-3.2.4.dist-info/top_level.txt
httpie-3.2.4.dist-info/RECORD
