Metadata-Version: 2.1
Name: httpie
Version: 3.2.4
Summary: HTTPie: modern, user-friendly command-line HTTP client for the API era.
Home-page: https://httpie.io/
Author: Jakub Roztocil
Author-email: jakub@roztocil.co
License: BSD
Project-URL: GitHub, https://github.com/httpie/cli
Project-URL: Twitter, https://twitter.com/httpie
Project-URL: Discord, https://httpie.io/discord
Project-URL: Documentation, https://httpie.io/docs
Project-URL: Online Demo, https://httpie.io/run
Classifier: Development Status :: 5 - Production/Stable
Classifier: Programming Language :: Python
Classifier: Programming Language :: Python :: 3 :: Only
Classifier: Environment :: Console
Classifier: Intended Audience :: Developers
Classifier: Intended Audience :: System Administrators
Classifier: License :: OSI Approved :: BSD License
Classifier: Topic :: Internet :: WWW/HTTP
Classifier: Topic :: Software Development
Classifier: Topic :: System :: Networking
Classifier: Topic :: Terminals
Classifier: Topic :: Text Processing
Classifier: Topic :: Utilities
Requires-Python: >=3.7
License-File: LICENSE
License-File: AUTHORS.md
Requires-Dist: pip
Requires-Dist: charset_normalizer>=2.0.0
Requires-Dist: defusedxml>=0.6.0
Requires-Dist: requests[socks]>=2.22.0
Requires-Dist: Pygments>=2.5.2
Requires-Dist: requests-toolbelt>=0.9.1
Requires-Dist: multidict>=4.7.0
Requires-Dist: setuptools
Requires-Dist: importlib-metadata>=1.4.0; python_version < "3.8"
Requires-Dist: rich>=9.10.0
Requires-Dist: colorama>=0.2.4; sys_platform == "win32"
Provides-Extra: dev
Requires-Dist: pytest; extra == "dev"
Requires-Dist: pytest-httpbin>=0.0.6; extra == "dev"
Requires-Dist: responses; extra == "dev"
Requires-Dist: pytest-mock; extra == "dev"
Requires-Dist: werkzeug<2.1.0; extra == "dev"
Requires-Dist: flake8; extra == "dev"
Requires-Dist: flake8-comprehensions; extra == "dev"
Requires-Dist: flake8-deprecated; extra == "dev"
Requires-Dist: flake8-mutable; extra == "dev"
Requires-Dist: flake8-tuple; extra == "dev"
Requires-Dist: pyopenssl; extra == "dev"
Requires-Dist: pytest-cov; extra == "dev"
Requires-Dist: pyyaml; extra == "dev"
Requires-Dist: twine; extra == "dev"
Requires-Dist: wheel; extra == "dev"
Requires-Dist: Jinja2; extra == "dev"
Provides-Extra: test
Requires-Dist: pytest; extra == "test"
Requires-Dist: pytest-httpbin>=0.0.6; extra == "test"
Requires-Dist: responses; extra == "test"
Requires-Dist: pytest-mock; extra == "test"
Requires-Dist: werkzeug<2.1.0; extra == "test"
